Tools_java/__init__.py
Tools_java/generate_refactoring.py
Tools_java/java_tools.py
Tools_java/processing_source_code.py
Tools_java/refactoring_methods.py
Tools_java/util.py
Tools_java-0.1.dist-info/METADATA
Tools_java-0.1.dist-info/WHEEL
Tools_java-0.1.dist-info/top_level.txt
Tools_java-0.1.dist-info/RECORD
