Metadata-Version: 2.1
Name: Tools-java
Version: 0.1
Requires-Dist: numpy
Requires-Dist: pandas
